codemmlu/__init__.py
codemmlu/__main__.py
codemmlu/evaluator.py
codemmlu/task_utils.py
codemmlu/backends/__init__.py
codemmlu/backends/base.py
codemmlu/backends/hf.py
codemmlu/backends/vllm.py
codemmlu/prompts/__init__.py
codemmlu/prompts/_codecomp.py
codemmlu/prompts/_coderepair.py
codemmlu/prompts/_defect.py
codemmlu/prompts/_fim.py
codemmlu/prompts/_general.py
codemmlu-0.0.2.1.dist-info/LICENSE
codemmlu-0.0.2.1.dist-info/METADATA
codemmlu-0.0.2.1.dist-info/WHEEL
codemmlu-0.0.2.1.dist-info/entry_points.txt
codemmlu-0.0.2.1.dist-info/top_level.txt
codemmlu-0.0.2.1.dist-info/RECORD
