Metadata-Version: 2.1
Name: codemmlu
Version: 0.0.2.1
Summary: CodeMMLU Evaluator: A framework for evaluating language models on CodeMMLU benchmark.
Author-email: Dung Manh Nguyen <dungnm.workspace@gmail.com>
Project-URL: Homepage, https://fsoft-ai4code.github.io/codemmlu/
Project-URL: Bug Tracker, https://github.com/FSoft-AI4Code/CodeMMLU/issues
Classifier: Programming Language :: Python :: 3
Classifier: License :: OSI Approved :: MIT License
Classifier: Operating System :: OS Independent
Requires-Python: >=3.9
License-File: LICENSE
Requires-Dist: transformers>=4.39.0
Requires-Dist: datasets>=2.17.1
Requires-Dist: accelerate>=0.27.2
Requires-Dist: deepspeed>=0.13.2
Requires-Dist: peft>=0.10.0
Requires-Dist: vllm
